{
  "scripts-engines-and-systems.json": {
    "s.7cb98c0c6527401e": "魔法工具栏：以下是你可用来管理魔法工具栏的指令（含方括号）。<BR><BR>[deathspell1 - 打开第1个死亡骑士法术栏编辑器。<BR><BR>[deathspell2 - 打开第2个死亡骑士法术栏编辑器。<BR><BR>[deathtool1 - 打开第1个死亡骑士法术栏。<BR><BR>[deathtool2 - 打开第2个死亡骑士法术栏。<BR><BR>[deathclose1 - 关闭第1个死亡骑士法术栏。<BR><BR>[deathclose2 - 关闭第2个死亡骑士法术栏。<BR><BR>以下指令可直接输入快速施法或设置快捷键：<BR><BR>[DKBanish<BR>    施放驱逐<BR><BR>[DKDemonicTouch<BR>    施放恶魔之触<BR><BR>[DKDevilPact<BR>    施放魔鬼契约<BR><BR>[DKGrimReaper<BR>    施放死神<BR><BR>[DKHagHand<BR>    施放巫婆之手<BR><BR>[DKHellfire<BR>    施放狱火<BR><BR>[DKLucifersBolt<BR>    施放路西法之箭<BR><BR>[DKOrbOrcus<BR>    施放奥库斯之球<BR><BR>[DKShieldHate<BR>    施放仇恨之盾<BR><BR>[DKSoulReaper<BR>    施放灵魂收割者<BR><BR>[DKStrengthSteel<BR>    施放钢铁之力<BR><BR>[DKStrike<BR>    施放猛击<BR><BR>[DKSuccubusSkin<BR>    施放魅魔之肤<BR><BR>[DKWrath<BR>    施放愤怒<BR><BR>",
    "s.7d2a5b379f5f370f": "」。该墓穴外部入口的最后已知坐标是：<br><br>",
    "s.7e8ee00d962e118f": "圣者卡戈斯<BR>索萨利亚大陆：远古金字塔<BR>{0}<BR><BR>",
    "s.7ff1e27aa6c997f9": "关闭快捷栏",
    "s.81409007ac56e0dd": "你不是西斯！",
    "s.831f3d30931d6f58": "毒药悲歌",
    "s.885b74d4c9cdf49a": "大幅提升目标的力度，持续短暂时间。",
    "s.8870dc9d0f1ab34d": "技能：",
    "s.89848446d8e76c49": "你需要杜拉钢！",
    "s.8e184a29888cf36f": "团队范围效果，提升全队力量。",
    "s.973670e1df0e5646": "若你找到带有降低药材品质属性的魔法物品，施法所需的体力将按该值比例减少。",
    "s.9a09260836131dbf": "建造激光剑",
    "s.a270746605e6e810": "药材：",
    "s.a2dc9c1a1128fe83": "打开纵向快捷栏",
    "s.a2e9ebcacd7cfbac": "你与西斯合为一体",
    "s.a57977677ee962b5": "蒙杜伊兹·德法尔领主<BR>索萨利亚大陆：线索地牢<BR>{0}<BR><BR>",
    "s.a7c95e229de49f65": "死亡骑士的敌人受到九层地狱恶魔能量的伤害。",
    "s.a7ef0d083abb54b8": "降低目标的毒药抗性。",
    "s.ad2394878ee8a3f7": "你需要一颗宝石！",
    "s.af372686cfabca91": "拉克斯的米拉尔王子<BR>索萨利亚大陆：地狱之火<BR>{0}<BR><BR>",
    "s.af5e9c266f3d8bd5": "要学习死亡骑士之道，你必须在遍布邪恶行径的同时掌握骑士艺术，避免业力影响。你必须寻找卡斯的14位弟子骑士，学习他们各自掌握的力量。找到他们的安息之地，念出他们的名字，获取蕴含其知识的颅骨。将颅骨放入此书将提升法术潜力——但动作要快。任何人召唤颅骨都将使其无视位置显现，甚至从持有者手中夺走。你需要灵魂之力来施展此等魔法。寻找携带金币的人形生物（如强盗、兽人、泰坦、地精或巨魔），在左手持灯时将其击杀。他们的金币将化为尘土，而你的魂灯将积蓄力量——使用魔法时则会消耗。释放力量时无需持灯，仅收集灵魂时需要。魂灯也无需随身携带——死亡魔法将从其所在之处汲取灵魂。{0}虽然大多数魔法仅依赖你的骑士技能，但部分元素在业力越低时效果越强。前进吧，死亡骑士，将我们的秩序带回此界。但请当心，死亡骑士——强大的死亡骑士往往不为城中街道所容，可能遭到当场攻击。",
    "s.c75d7b6115de5dd2": "」。<br><br>"
  }
}